CoffeeAI/__init__.py
CoffeeAI/coffeeai.py
coffeeai-0.1.0.dist-info/METADATA
coffeeai-0.1.0.dist-info/WHEEL
coffeeai-0.1.0.dist-info/top_level.txt
coffeeai-0.1.0.dist-info/RECORD
