Metadata-Version: 2.2
Name: CoffeeAI
Version: 0.1.0
Summary: A neural network library for CoffeeAI.
Home-page: https://github.com/yourusername/coffeeai
Author: OUBStudios
Author-email: oubdocs.main@example.com
Classifier: Programming Language :: Python :: 3
Classifier: License :: OSI Approved :: MIT License
Classifier: Operating System :: OS Independent
Requires-Python: >=3.6
Requires-Dist: flask
Requires-Dist: numpy
Dynamic: author
Dynamic: author-email
Dynamic: classifier
Dynamic: home-page
Dynamic: requires-dist
Dynamic: requires-python
Dynamic: summary
